django_theme/__init__.py
django_theme/admin.py
django_theme/apps.py
django_theme/models.py
django_theme/urls.py
django_theme/views.py
django_theme/libs/__init__.py
django_theme/libs/code.py
django_theme/libs/test.py
django_theme/libs/tests/__init__.py
django_theme/libs/tests/test_assert.py
django_theme/libs/tests/test_code.py
django_theme/migrations/0001_initial.py
django_theme/migrations/0002_theme_login_logo.py
django_theme/migrations/0003_auto_20211015_1128.py
django_theme/migrations/__init__.py
django_theme/tests/__init__.py
django_theme/tests/case.py
django_theme/tests/test_models.py
django_theme/tests/test_system_style.py
django_theme/tests/test_without_theme.py
django_theme/tests/theme.py
django_sca_theme-0.2.0.dist-info/LICENSE
django_sca_theme-0.2.0.dist-info/METADATA
django_sca_theme-0.2.0.dist-info/WHEEL
django_sca_theme-0.2.0.dist-info/top_level.txt
django_sca_theme-0.2.0.dist-info/RECORD
