Metadata-Version: 2.1
Name: django-sca-theme
Version: 0.2.0
Summary: A Django app to config project theme
Home-page: https://gitee.com/
Author: svtter
Author-email: hao.xiu@beijing-epoch.com
License: NOT OPEN FOR EVERYONE # Example license
Platform: UNKNOWN
Classifier: Environment :: Web Environment
Classifier: Framework :: Django
Classifier: Framework :: Django :: 2.2
Classifier: Intended Audience :: Developers
Classifier: Operating System :: OS Independent
Classifier: Programming Language :: Python
Classifier: Programming Language :: Python :: 3
Classifier: Programming Language :: Python :: 3 :: Only
Classifier: Programming Language :: Python :: 3.6
Classifier: Programming Language :: Python :: 3.7
Classifier: Programming Language :: Python :: 3.8
Classifier: Topic :: Internet :: WWW/HTTP
Classifier: Topic :: Internet :: WWW/HTTP :: Dynamic Content
Requires-Python: >=3.6
License-File: LICENSE
Requires-Dist: Django (>=2.2)
Requires-Dist: djangorestframework (>=3.1)
Requires-Dist: Pillow (>=8.3.2)
